{"id":"a81c5955-8060-4c02-a7ee-ccc43d5f1b6d","timestamp":1721058047257,"matcher":{"static":{},"wildcard":{},"dynamic":{}},"prerendered":["/","/chatbox","/about","/contact","/donate","/services","/projects","/all","/people","/people/people","/projects/1","/projects/2","/projects/3","/projects/4","/projects/5","/people/2","/people/1","/people/4","/people/6","/people/3","/people/5","/people/12","/people/11","/people/7","/people/9","/people/10","/people/8","/people/13","/people/15","/people/14","/people/16","/people/17","/people/18","/people/20","/people/19","/people/21"]}